bin/extract-id.py
ckanext/__init__.py
ckanext/ytp/__init__.py
ckanext/ytp/comments/__init__.py
ckanext/ytp/comments/bad_words.txt
ckanext/ytp/comments/email_notifications.py
ckanext/ytp/comments/good_words.txt
ckanext/ytp/comments/helpers.py
ckanext/ytp/comments/model.py
ckanext/ytp/comments/notification_helpers.py
ckanext/ytp/comments/notification_models.py
ckanext/ytp/comments/plugin.py
ckanext/ytp/comments/request_helpers.py
ckanext/ytp/comments/util.py
ckanext/ytp/comments/cli/__init__.py
ckanext/ytp/comments/cli/click_cli.py
ckanext/ytp/comments/cli/command.py
ckanext/ytp/comments/cli/paster_cli.py
ckanext/ytp/comments/controllers/__init__.py
ckanext/ytp/comments/controllers/blueprints.py
ckanext/ytp/comments/controllers/pylons_controllers.py
ckanext/ytp/comments/logic/__init__.py
ckanext/ytp/comments/logic/action/__init__.py
ckanext/ytp/comments/logic/action/create.py
ckanext/ytp/comments/logic/action/delete.py
ckanext/ytp/comments/logic/action/get.py
ckanext/ytp/comments/logic/action/update.py
ckanext/ytp/comments/logic/auth/__init__.py
ckanext/ytp/comments/logic/auth/create.py
ckanext/ytp/comments/logic/auth/delete.py
ckanext/ytp/comments/logic/auth/get.py
ckanext/ytp/comments/logic/auth/update.py
ckanext/ytp/comments/plugin_mixins/__init__.py
ckanext/ytp/comments/plugin_mixins/flask_plugin.py
ckanext/ytp/comments/public/javascript/comment_validation.js
ckanext/ytp/comments/public/javascript/comments.css
ckanext/ytp/comments/public/javascript/comments.js
ckanext/ytp/comments/public/javascript/confirm_mute_content_item.js
ckanext/ytp/comments/public/javascript/flag-comment.js
ckanext/ytp/comments/public/javascript/follow_or_mute_notifications.js
ckanext/ytp/comments/public/javascript/webassets.yml
ckanext/ytp/comments/templates/admin/config.html
ckanext/ytp/comments/templates/emails/bodies/notification-flagged-comment.txt
ckanext/ytp/comments/templates/emails/bodies/notification-new-comment.txt
ckanext_ytp_comments-2.5.3.dist-info/METADATA
ckanext_ytp_comments-2.5.3.dist-info/WHEEL
ckanext_ytp_comments-2.5.3.dist-info/entry_points.txt
ckanext_ytp_comments-2.5.3.dist-info/top_level.txt
ckanext_ytp_comments-2.5.3.dist-info/RECORD
