Metadata-Version: 2.4
Name: ckanext-ytp-comments
Version: 2.5.3
Summary: Adds commenting on datasets and data requests
Author-email: ThrawnCA <carl.antuar@smartservice.qld.gov.au>, Queensland Online <qol.development@smartservice.qld.gov.au>, "William Dutton (duttonw)" <william.dutton@qld.gov.au>
Maintainer-email: ThrawnCA <carl.antuar@smartservice.qld.gov.au>, Queensland Online <qol.development@smartservice.qld.gov.au>, "William Dutton (duttonw)" <william.dutton@qld.gov.au>
License: AGPL
Project-URL: Homepage, https://github.com/qld-gov-au/ckanext-ytp-comments
Keywords: CKAN,extension,comments
Classifier: Development Status :: 5 - Production/Stable
Classifier: License :: OSI Approved :: GNU Affero General Public License v3 or later (AGPLv3+)
Classifier: Programming Language :: Python :: 3.8
Classifier: Programming Language :: Python :: 3.9
Classifier: Programming Language :: Python :: 3.10
Requires-Python: >=3.8
